protobase/__init__.py
protobase/annotations.py
protobase/attr.py
protobase/core.py
protobase/settings.py
protobase/traits/__init__.py
protobase/traits/cmp.py
protobase/traits/consed.py
protobase/traits/dynamic_attrs.py
protobase/traits/hash.py
protobase/traits/init.py
protobase/traits/inmutable.py
protobase/traits/repr.py
protobase/traits/weak.py
protobase/utils.py
protobase-0.1.1.dist-info/LICENSE
protobase-0.1.1.dist-info/METADATA
protobase-0.1.1.dist-info/WHEEL
protobase-0.1.1.dist-info/RECORD
