Metadata-Version: 2.1
Name: protobase
Version: 0.1.1
Summary: Protobase is a simple Python library designed to serve as a foundational element in the creation and composition of object classes.
License: MIT
Author: jdavidls
Author-email: jdavidls@protonmail.com
Requires-Python: >=3.9,<4.0
Classifier: License :: OSI Approved :: MIT License
Classifier: Programming Language :: Python :: 3
Classifier: Programming Language :: Python :: 3.9
Classifier: Programming Language :: Python :: 3.10
Classifier: Programming Language :: Python :: 3.11
Classifier: Programming Language :: Python :: 3.12
